xlite/_C.cpython-311-aarch64-linux-gnu.so
xlite/_C.pyi
xlite/__init__.py
xlite/py.typed
xlite/lib/libxlite.so
xlite/lib/libxlite_kernels_bf16_npu.so
xlite/lib/libxlite_kernels_common_npu.so
xlite/lib/libxlite_kernels_f16_npu.so
xlite-0.1.0rc1.dist-info/METADATA
xlite-0.1.0rc1.dist-info/WHEEL
xlite-0.1.0rc1.dist-info/top_level.txt
xlite-0.1.0rc1.dist-info/RECORD
