Metadata-Version: 2.4
Name: xlite
Version: 0.1.0rc1
Summary: A lightweight, effective and easy-to-extend inference runtime
Home-page: https://gitee.com/openeuler/GVirt
Author: Huawei Euler OS Team
License: MulanPSL2
Classifier: Programming Language :: Python :: 3.9
Classifier: Programming Language :: Python :: 3.10
Classifier: Programming Language :: Python :: 3.11
Classifier: Topic :: Scientific/Engineering :: Artificial Intelligence
Requires-Python: >=3.9
Requires-Dist: pybind11
Requires-Dist: torch>=2.5.1
Dynamic: author
Dynamic: classifier
Dynamic: description
Dynamic: description-content-type
Dynamic: home-page
Dynamic: license
Dynamic: requires-dist
Dynamic: requires-python
Dynamic: summary
